{
    "$schema": "http://json-schema.org/draft-07/schema#",
    "type": "object",
    "properties": {
        "credential_issuer": {
            "type": "string",
            "format": "uri",
            "description": "The Credential Issuer's identifier",
            "examples": [
                "https://example.com/issuer"
            ]
        },
        "authorization_servers": {
            "type": "array",
            "items": {
                "type": "string",
                "format": "uri"
            },
            "description": "Array of OAuth 2.0 Authorization Server identifiers."
        },
        "credential_endpoint": {
            "type": "string",
            "format": "uri",
            "description": "URL of the Credential Issuer's Credential Endpoint."
        },
        "nonce_endpoint": {
            "type": "string",
            "format": "uri",
            "description": "URL of the Credential Issuer's Nonce Endpoint."
        },
        "deferred_credential_endpoint": {
            "type": "string",
            "format": "uri",
            "description": "URL of the Credential Issuer's Deferred Credential Endpoint."
        },
        "notification_endpoint": {
            "type": "string",
            "format": "uri",
            "description": "URL of the Credential Issuer's Notification Endpoint."
        },
        "credential_response_encryption": {
            "type": "object",
            "properties": {
                "alg_values_supported": {
                    "type": "array",
                    "items": {
                        "type": "string",
                        "enum": [
                            "ES256",
                            "EdDSA",
                            "RS256"
                        ]
                    }
                },
                "enc_values_supported": {
                    "type": "array",
                    "items": {
                        "type": "string",
                        "enum": [
                            "A128CBC-HS256",
                            "A128GCM"
                        ]
                    }
                },
                "encryption_required": {
                    "type": "boolean"
                }
            },
            "required": [
                "alg_values_supported",
                "enc_values_supported",
                "encryption_required"
            ]
        },
        "batch_credential_issuance": {
            "type": "object",
            "properties": {
                "batch_size": {
                    "type": "integer",
                    "minimum": 1
                }
            },
            "required": [
                "batch_size"
            ]
        },
        "signed_metadata": {
            "type": "string",
            "description": "JWT containing Credential Issuer metadata parameters as claims."
        },
        "display": {
            "type": "array",
            "items": {
                "type": "object",
                "properties": {
                    "name": {
                        "type": "string"
                    },
                    "locale": {
                        "type": "string"
                    },
                    "logo": {
                        "type": "object",
                        "properties": {
                            "uri": {
                                "type": "string",
                                "format": "uri"
                            },
                            "alt_text": {
                                "type": "string"
                            }
                        },
                        "required": [
                            "uri"
                        ]
                    }
                }
            }
        },
        "credential_configurations_supported": {
            "type": "object",
            "additionalProperties": {
                "type": "object",
                "properties": {
                    "format": {
                        "type": "string"
                    },
                    "scope": {
                        "type": "string"
                    },
                    "cryptographic_binding_methods_supported": {
                        "type": "array",
                        "items": {
                            "type": "string",
                            "enum": [
                                "JWK",
                                "jwk",
                                "did",
                                "did:web",
                                "did:ebsi",
                                "did:jwk",
                                "did:dyne",
                                "did:dyne:sandbox.signroom",
                                "did:key",
                                "cose_key"
                            ]
                        }
                    },
                    "credential_signing_alg_values_supported": {
                        "type": "array",
                        "items": {
                            "type": "string",
                            "enum": [
                                "ES256",
                                "EdDSA",
                                "Ed25519Signature2020",
                                "RS256",
                                "ES256K",
                                "RSA",
                                "RsaSignature2018"
                            ]
                        }
                    },
                    "proof_types_supported": {
                        "type": "object",
                        "additionalProperties": {
                            "type": "object",
                            "properties": {
                                "proof_signing_alg_values_supported": {
                                    "type": "array",
                                    "items": {
                                        "type": "string",
                                        "enum": [
                                            "ES256",
                                            "EdDSA",
                                            "PS256",
                                            "RS256"
                                        ]
                                    }
                                },
                                "key_attestations_required": {
                                    "type": "object",
                                    "properties": {
                                        "key_storage": {
                                            "type": "array",
                                            "items": {
                                                "type": "string"
                                            }
                                        },
                                        "user_authentication": {
                                            "type": "array",
                                            "items": {
                                                "type": "string"
                                            }
                                        }
                                    }
                                }
                            },
                            "required": [
                                "proof_signing_alg_values_supported"
                            ]
                        }
                    },
                    "display": {
                        "type": "array",
                        "items": {
                            "type": "object",
                            "properties": {
                                "name": {
                                    "type": "string"
                                },
                                "locale": {
                                    "type": "string"
                                },
                                "logo": {
                                    "type": "object",
                                    "properties": {
                                        "url": {
                                            "type": "string",
                                            "format": "uri"
                                        },
                                        "uri": {
                                            "type": "string",
                                            "format": "uri"
                                        },
                                        "alt_text": {
                                            "type": "string"
                                        }
                                    },
                                    "oneOf": [
                                        {
                                            "required": [
                                                "uri"
                                            ]
                                        },
                                        {
                                            "required": [
                                                "url"
                                            ]
                                        }
                                    ],
                                    "additionalProperties": false
                                }
                            },
                            "required": [
                                "name"
                            ]
                        }
                    },
                    "credential_definition": {
                        "type": "object",
                        "properties": {
                            "type": {
                                "type": "array",
                                "items": {
                                    "type": "string"
                                }
                            },
                            "credentialSubject": {
                                "type": "object",
                                "additionalProperties": {
                                    "type": "object",
                                    "properties": {
                                        "mandatory": {
                                            "type": "boolean"
                                        },
                                        "display": {
                                            "type": "array",
                                            "items": {
                                                "type": "object",
                                                "properties": {
                                                    "name": {
                                                        "type": "string"
                                                    },
                                                    "locale": {
                                                        "type": "string"
                                                    }
                                                },
                                                "required": [
                                                    "name"
                                                ]
                                            }
                                        }
                                    }
                                }
                            }
                        }
                    }
                },
                "required": [
                    "format"
                ]
            }
        }
    },
    "required": [
        "credential_issuer",
        "credential_endpoint",
        "credential_configurations_supported"
    ]
}
